redis_server/__init__.py
redis_server/bin/redis-cli
redis_server/bin/redis-server
redis_server-6.0.8.dist-info/LICENSE
redis_server-6.0.8.dist-info/WHEEL
redis_server-6.0.8.dist-info/METADATA
redis_server-6.0.8.dist-info/RECORD
