Metadata-Version: 2.1
Name: redis-server
Version: 6.0.8
Summary: 
Home-page: https://github.com/private-pypi/redis-server
License: MIT
Keywords: redis,server
Author: huntzhan
Author-email: huntzhan.dev@gmail.com
Requires-Python: >=3,<4
Classifier: License :: OSI Approved :: MIT License
Classifier: Programming Language :: Python :: 3
Classifier: Programming Language :: Python :: 3.4
Classifier: Programming Language :: Python :: 3.5
Classifier: Programming Language :: Python :: 3.6
Classifier: Programming Language :: Python :: 3.7
Classifier: Programming Language :: Python :: 3.8
Classifier: Programming Language :: Python :: 3.9
Project-URL: Repository, https://github.com/private-pypi/redis-server
